selenium_fetch/__init__.py
selenium_fetch/py.typed
selenium_fetch-0.1.1.dist-info/LICENSE
selenium_fetch-0.1.1.dist-info/WHEEL
selenium_fetch-0.1.1.dist-info/METADATA
selenium_fetch-0.1.1.dist-info/RECORD
