Metadata-Version: 2.1
Name: selenium-fetch
Version: 0.1.1
Summary: access `fetch()` with selenium!
Home-page: https://github.com/aprilahijriyan/selenium-fetch
License: MIT
Keywords: selenium,fetch,undetected-chromedriver,cloudflare
Author: aprilahijriyan
Author-email: hijriyan23@gmail.com
Requires-Python: >=3.9,<4.0
Classifier: Development Status :: 4 - Beta
Classifier: Environment :: Web Environment
Classifier: Intended Audience :: Developers
Classifier: License :: OSI Approved :: MIT License
Classifier: Operating System :: OS Independent
Classifier: Programming Language :: Python
Classifier: Programming Language :: Python :: 3
Classifier: Programming Language :: Python :: 3.9
Classifier: Programming Language :: Python :: 3.10
Classifier: Programming Language :: Python :: 3.11
Requires-Dist: pydantic (>=1.10.6,<2.0.0)
Requires-Dist: selenium (>=4.8.2,<5.0.0)
Project-URL: Repository, https://github.com/aprilahijriyan/selenium-fetch
